LICENSE.txt
MANIFEST.in
README.txt
setup.py
bin/checkopy
bin/checkopy.py
chkopy/__init__.py
chkopy.egg-info/PKG-INFO
chkopy.egg-info/SOURCES.txt
chkopy.egg-info/dependency_links.txt
chkopy.egg-info/top_level.txt