Metadata-Version: 1.0
Name: chkopy
Version: 0.1.7b0
Summary: A tool to simplify checksum and copying procedures
Home-page: https://pypi.python.org/pypi/chkopy
Author: Christopher McFetridge
Author-email: crmcfetridge@gmail.com
License: LICENSE.txt
Platform: UNKNOWN
